Tracker/__init__.py
Tracker/__version__.py
Tracker/event.py
Tracker/main.py
Tracker/menu.py
Tracker/spider.py
Tracker/update.py
Tracker/tests/__init__.py
Tracker/tests/prog.py
Tracker/tests/test_event.py
Tracker/tests/test_spider.py
BT_Tracker-0.2.5.dist-info/LICENSE
BT_Tracker-0.2.5.dist-info/METADATA
BT_Tracker-0.2.5.dist-info/WHEEL
BT_Tracker-0.2.5.dist-info/entry_points.txt
BT_Tracker-0.2.5.dist-info/top_level.txt
BT_Tracker-0.2.5.dist-info/RECORD
