Metadata-Version: 2.1
Name: BT-Tracker
Version: 0.2.5
Summary: BT Trackers Updater of the Aria2, based on Command Line Interface.
Home-page: https://github.com/nordwind80/BT-Tracker
Author: eaglewings
Author-email: eaglewings.yi@gmail.com
License: MIT
Keywords: aria2,Tracker,cli,updater
Platform: UNKNOWN
Classifier: Environment :: Console
Classifier: License :: OSI Approved :: MIT License
Classifier: Operating System :: MacOS :: MacOS X
Classifier: Programming Language :: Python :: 3.6
Classifier: Programming Language :: Python :: 3.7
Requires-Dist: requests
